README.md
setup.py
alibabacloud_pds_sdk/__init__.py
alibabacloud_pds_sdk/client.py
alibabacloud_pds_sdk/models.py
alibabacloud_pds_sdk.egg-info/PKG-INFO
alibabacloud_pds_sdk.egg-info/SOURCES.txt
alibabacloud_pds_sdk.egg-info/dependency_links.txt
alibabacloud_pds_sdk.egg-info/requires.txt
alibabacloud_pds_sdk.egg-info/top_level.txt